tests/__init__.py
tests/tune/__init__.py
tests/tune/_utils/__init__.py
tests/tune/_utils/test_collections.py
tests/tune/_utils/test_execution.py
tests/tune/_utils/test_math.py
tests/tune/_utils/test_values.py
tests/tune/api/__init__.py
tests/tune/api/test_factory.py
tests/tune/concepts/__init__.py
tests/tune/concepts/test_checkpoint.py
tests/tune/concepts/test_dataset.py
tests/tune/concepts/test_flow.py
tests/tune/concepts/test_logger.py
tests/tune/concepts/space/__init__.py
tests/tune/concepts/space/test_parameters.py
tests/tune/concepts/space/test_space.py
tests/tune/iterative/__init__.py
tests/tune/iterative/test_asha.py
tests/tune/iterative/test_objective.py
tests/tune/iterative/test_sha.py
tests/tune/iterative/test_study.py
tests/tune/noniterative/__init__.py
tests/tune/noniterative/test_convert.py
tests/tune/noniterative/test_stopper.py
tests/tune/noniterative/test_study.py
tests/tune_hyperopt/__init__.py
tests/tune_hyperopt/test_local_optimizer.py
tests/tune_notebook/__init__.py
tests/tune_notebook/test_monitors.py
tests/tune_optuna/__init__.py
tests/tune_optuna/test_local_optimizer.py
tests/tune_sklearn/__init__.py
tests/tune_sklearn/test_objective.py
tests/tune_sklearn/test_suggest.py
tests/tune_sklearn/test_utils.py
tests/tune_tensorflow/__init__.py
tests/tune_tensorflow/mock.py
tests/tune_tensorflow/test_objective.py
tests/tune_tensorflow/test_suggest.py
tests/tune_tensorflow/test_utils.py
tune/__init__.py
tune/constants.py
tune/exceptions.py
tune/_utils/__init__.py
tune/_utils/collections.py
tune/_utils/execution.py
tune/_utils/math.py
tune/_utils/serialization.py
tune/_utils/test.py
tune/_utils/values.py
tune/api/__init__.py
tune/api/factory.py
tune/api/optimize.py
tune/api/suggest.py
tune/concepts/__init__.py
tune/concepts/checkpoint.py
tune/concepts/dataset.py
tune/concepts/logger.py
tune/concepts/flow/__init__.py
tune/concepts/flow/judge.py
tune/concepts/flow/report.py
tune/concepts/flow/trial.py
tune/concepts/space/__init__.py
tune-0.1.6.dist-info/LICENSE
tune-0.1.6.dist-info/METADATA
tune-0.1.6.dist-info/WHEEL
tune-0.1.6.dist-info/entry_points.txt
tune-0.1.6.dist-info/top_level.txt
tune-0.1.6.dist-info/RECORD
