Metadata-Version: 2.1
Name: tune
Version: 0.1.6
Summary: An abstraction layer for hyper parameter tuning
Home-page: http://github.com/fugue-project/tune
Author: Han Wang
Author-email: goodwanghan@gmail.com
License: Apache-2.0
Keywords: hyper parameter hyperparameter tuning tune tuner optimzation
Platform: UNKNOWN
Classifier: Development Status :: 3 - Alpha
Classifier: Intended Audience :: Developers
Classifier: Topic :: Software Development :: Libraries :: Python Modules
Classifier: License :: OSI Approved :: Apache Software License
Classifier: Programming Language :: Python :: 3.8
Classifier: Programming Language :: Python :: 3.9
Classifier: Programming Language :: Python :: 3.10
Classifier: Programming Language :: Python :: 3.11
Classifier: Programming Language :: Python :: 3.12
Classifier: Programming Language :: Python :: 3 :: Only
Requires-Python: >=3.8
Requires-Dist: fugue
Requires-Dist: cloudpickle
Requires-Dist: triad>=0.8.4
Requires-Dist: fs
Provides-Extra: all
Requires-Dist: hyperopt; extra == "all"
Requires-Dist: optuna; extra == "all"
Requires-Dist: seaborn; extra == "all"
Requires-Dist: tensorflow; extra == "all"
Requires-Dist: fugue-jupyter; extra == "all"
Requires-Dist: scikit-learn; extra == "all"
Requires-Dist: mlflow; extra == "all"
Provides-Extra: hyperopt
Requires-Dist: hyperopt; extra == "hyperopt"
Provides-Extra: mlflow
Requires-Dist: mlflow; extra == "mlflow"
Provides-Extra: notebook
Requires-Dist: fugue-jupyter; extra == "notebook"
Requires-Dist: seaborn; extra == "notebook"
Provides-Extra: optuna
Requires-Dist: optuna; extra == "optuna"
Provides-Extra: sklearn
Requires-Dist: scikit-learn; extra == "sklearn"
Provides-Extra: tensorflow
Requires-Dist: tensorflow; extra == "tensorflow"
